eidospy/__init__.py
eidospy/dataspace.py
eidospy/doc.py
eidospy/eidos.py
eidospy/rows.py
eidospy/table.py
eidospy-0.0.1.dist-info/LICENSE
eidospy-0.0.1.dist-info/METADATA
eidospy-0.0.1.dist-info/WHEEL
eidospy-0.0.1.dist-info/top_level.txt
eidospy-0.0.1.dist-info/RECORD
