Metadata-Version: 2.1
Name: eidospy
Version: 0.0.1
Summary: Python SDK for Eidos
Author-email: mayneyao <i@gine.me>
Project-URL: Homepage, https://github.com/mayneyao/eidospy
Project-URL: Issues, https://github.com/mayneyao/eidospy/issues
Classifier: Programming Language :: Python :: 3
Classifier: License :: OSI Approved :: MIT License
Classifier: Operating System :: OS Independent
Requires-Python: >=3.8
License-File: LICENSE
